{"numDocumentoIdObligado":"891200240","numFactura":"2104503","tipoNota":null,"numNota":null,"usuarios":[{"tipoDocumentoIdentificacion":"RC","numDocumentoIdentificacion":"1081287111","tipoUsuario":"01","fechaNacimiento":"2018-07-11","codSexo":"M","codPaisResidencia":"170","codMunicipioResidencia":"52480","codZonaTerritorialResidencia":"01","incapacidad":"NO","consecutivo":1,"codPaisOrigen":"170","servicios":{"consultas":[{"codPrestador":"520010028301","fechaInicioAtencion":"2025-02-14 10:43","numAutorizacion":"295423258","codConsulta":"890326","modalidadGrupoServicioTecSal":"01","grupoServicios":"01","codServicio":1102,"finalidadTecnologiaSalud":"16","causaMotivoAtencion":"38","codDiagnosticoPrincipal":"N500","codDiagnosticoRelacionado1":null,"codDiagnosticoRelacionado2":null,"codDiagnosticoRelacionado3":null,"tipoDiagnosticoPrincipal":"02","tipoDocumentoIdentificacion":"CC","numDocumentoIdentificacion":"36758838","vrServicio":61500,"conceptoRecaudo":"05","valorPagoModerador":0,"numFEVPagoModerador":"2102069","consecutivo":1}],"procedimientos":[{"codPrestador":"520010028301","fechaInicioAtencion":"2025-02-14 11:14","numAutorizacion":"295423258","idMIPRES":null,"codProcedimiento":"623001","viaIngresoServicioSalud":"02","modalidadGrupoServicioTecSal":"01","grupoServicios":"02","codServicio":1102,"finalidadTecnologiaSalud":"16","tipoDocumentoIdentificacion":"CC","numDocumentoIdentificacion":"12994086","codDiagnosticoPrincipal":"N500","codDiagnosticoRelacionado":null,"codComplicacion":null,"vrServicio":529400,"conceptoRecaudo":"01","valorPagoModerador":267455,"numFEVPagoModerador":"2102069","consecutivo":1},{"codPrestador":"520010028301","fechaInicioAtencion":"2025-02-14 11:14","numAutorizacion":"295423258","idMIPRES":null,"codProcedimiento":"623001","viaIngresoServicioSalud":"02","modalidadGrupoServicioTecSal":"01","grupoServicios":"02","codServicio":1102,"finalidadTecnologiaSalud":"16","tipoDocumentoIdentificacion":"CC","numDocumentoIdentificacion":"36758838","codDiagnosticoPrincipal":"N500","codDiagnosticoRelacionado":null,"codComplicacion":null,"vrServicio":302800,"conceptoRecaudo":"05","valorPagoModerador":0,"numFEVPagoModerador":"2102069","consecutivo":2},{"codPrestador":"520010028301","fechaInicioAtencion":"2025-02-14 11:14","numAutorizacion":"295423258","idMIPRES":null,"codProcedimiento":"623001","viaIngresoServicioSalud":"02","modalidadGrupoServicioTecSal":"01","grupoServicios":"02","codServicio":1102,"finalidadTecnologiaSalud":"16","tipoDocumentoIdentificacion":"CC","numDocumentoIdentificacion":"1085332370","codDiagnosticoPrincipal":"N500","codDiagnosticoRelacionado":null,"codComplicacion":null,"vrServicio":144700,"conceptoRecaudo":"05","valorPagoModerador":0,"numFEVPagoModerador":"2102069","consecutivo":3},{"codPrestador":"520010028301","fechaInicioAtencion":"2025-02-14 11:14","numAutorizacion":"295423258","idMIPRES":null,"codProcedimiento":"623001","viaIngresoServicioSalud":"02","modalidadGrupoServicioTecSal":"01","grupoServicios":"02","codServicio":1102,"finalidadTecnologiaSalud":"16","tipoDocumentoIdentificacion":"CC","numDocumentoIdentificacion":"12994086","codDiagnosticoPrincipal":"N500","codDiagnosticoRelacionado":null,"codComplicacion":null,"vrServicio":875700,"conceptoRecaudo":"05","valorPagoModerador":0,"numFEVPagoModerador":"2102069","consecutivo":4},{"codPrestador":"520010028301","fechaInicioAtencion":"2025-02-14 11:14","numAutorizacion":"295423258","idMIPRES":null,"codProcedimiento":"623001","viaIngresoServicioSalud":"02","modalidadGrupoServicioTecSal":"01","grupoServicios":"02","codServicio":1102,"finalidadTecnologiaSalud":"16","tipoDocumentoIdentificacion":"CC","numDocumentoIdentificacion":"12994086","codDiagnosticoPrincipal":"N500","codDiagnosticoRelacionado":null,"codComplicacion":null,"vrServicio":411600,"conceptoRecaudo":"05","valorPagoModerador":0,"numFEVPagoModerador":"2102069","consecutivo":5}],"hospitalizacion":[{"codPrestador":"520010028301","viaIngresoServicioSalud":"02","fechaInicioAtencion":"2025-02-14 00:00","numAutorizacion":"295423258","causaMotivoAtencion":"38","codDiagnosticoPrincipal":"Q531","codDiagnosticoPrincipalE":"N500","codDiagnosticoRelacionadoE1":null,"codDiagnosticoRelacionadoE2":null,"codDiagnosticoRelacionadoE3":null,"codComplicacion":null,"condicionDestinoUsuarioEgreso":"01","codDiagnosticoCausaMuerte":null,"fechaEgreso":"2025-02-14 10:43","consecutivo":1}]}}]}